[{"text":"Tính từ","level":0},{"text":"1. Có thể <a href=\"/wiki/nh%E1%BA%ADn\" title=\"nhận\">nhận</a>, có thể <a href=\"/wiki/ch%E1%BA%A5p_nh%E1%BA%ADn\" title=\"chấp nhận\">chấp nhận</a>.","level":1},{"text":"2. Có thể <a href=\"/wiki/th%E1%BB%ABa_nh%E1%BA%ADn\" title=\"thừa nhận\">thừa nhận</a>.","level":1},{"text":"3. <a href=\"/wiki/tho%E1%BA%A3\" class=\"mw-redirect\" title=\"thoả\">Thoả</a> đáng, làm <a href=\"/wiki/h%C3%A0i_l%C3%B2ng\" title=\"hài lòng\">hài lòng</a>; được <a href=\"/wiki/hoan_ngh%C3%AAnh\" title=\"hoan nghênh\">hoan nghênh</a>, được <a href=\"/wiki/t%C3%A1n_th%C6%B0%E1%BB%9Fng\" title=\"tán thưởng\">tán thưởng</a>.","level":1},{"text":"Tính từ","level":0},{"text":"1. <a href=\"/wiki/c%C3%B3_th%E1%BB%83\" title=\"có thể\">Có thể</a> <a href=\"/wiki/ch%E1%BA%A5p_nh%E1%BA%ADn\" title=\"chấp nhận\">chấp nhận</a>.","level":1},{"text":"<i>Conditions <b>acceptables</b></i> — điều kiện có thể chấp nhận","level":2},{"text":"<i>Prix <b>acceptables</b></i> — giá phải chăng","level":2}]