[{"text":"Danh từ","level":0},{"text":"1. Sự đổi, sự <a href=\"/wiki/thay_%C4%91%E1%BB%95i\" title=\"thay đổi\">thay đổi</a>, <a href=\"/wiki/s%E1%BB%B1_bi%E1%BA%BFn\" title=\"sự biến\">sự biến</a> đổi.","level":1},{"text":"<i>to undergo a complete <b>change</b></i> — thay đổi hoàn toàn","level":2},{"text":"<i>just for a <b>change</b></i> — để thay đổi một chút","level":2},{"text":"<i><b>change</b> for the better</i> — sự thay đổi tốt hơn","level":2},{"text":"<i><b>change</b> for the worse</i> — sự thay đổi xấu đi","level":2},{"text":"<i>a <b>change</b> of air</i> — sự thay đổi không khí, sự thay đổi môi trường","level":2},{"text":"<i>the changes of life</i> — những nỗi thăng trầm của cuộc sống","level":2},{"text":"<i><b>change</b> of mind (heart)</i> — sự thay đổi ý kiến, sự thay đổi ý định; sự thay đổi kế hoạch","level":2},{"text":"2. <a href=\"/wiki/tr%C4%83ng_non\" title=\"trăng non\">Trăng non</a>.","level":1},{"text":"3. Bộ <a href=\"/wiki/qu%E1%BA%A7n_%C3%A1o\" title=\"quần áo\">quần áo</a> <a href=\"/wiki/s%E1%BA%A1ch\" title=\"sạch\">sạch</a> (để dự phòng) ((cũng) a <a class=\"mw-selflink selflink\">change</a> <a href=\"/wiki/of\" title=\"of\">of</a> <a href=\"/wiki/clothes\" title=\"clothes\">clothes</a>).","level":1},{"text":"4. <a href=\"/wiki/ti%E1%BB%81n\" title=\"tiền\">Tiền</a> đổi, <a href=\"/wiki/ti%E1%BB%81n_l%E1%BA%BB\" title=\"tiền lẻ\">tiền lẻ</a>.","level":1},{"text":"5. <a href=\"/wiki/ti%E1%BB%81n\" title=\"tiền\">Tiền</a> <a href=\"/wiki/ph%E1%BB%A5\" title=\"phụ\">phụ</a> lại (cho khách hàng).","level":1},{"text":"6. <a href=\"/wiki/n%C6%A1i\" title=\"nơi\">Nơi</a> đổi <a href=\"/wiki/t%C3%A0u\" title=\"tàu\">tàu</a> <a href=\"/wiki/xe\" title=\"xe\">xe</a>.","level":1},{"text":"7. Sự <a href=\"/wiki/giao_d%E1%BB%8Bch\" title=\"giao dịch\">giao dịch</a> <a href=\"/wiki/ch%E1%BB%A9ng_kho%C3%A1n\" title=\"chứng khoán\">chứng khoán</a>; <a href=\"/wiki/th%E1%BB%8B_tr%C6%B0%E1%BB%9Dng\" title=\"thị trường\">thị trường</a> <a href=\"/wiki/ch%E1%BB%A9ng_kho%C3%A1n\" title=\"chứng khoán\">chứng khoán</a> (ở Luân-đôn) ((cũng) <a href=\"/w/index.php?title=Change&amp;action=edit&amp;redlink=1\" class=\"new\" title=\"Change (trang không tồn tại)\">Change</a>, (viết tắt) của <a href=\"/w/index.php?title=Exchange&amp;action=edit&amp;redlink=1\" class=\"new\" title=\"Exchange (trang không tồn tại)\">Exchange</a>).","level":1},{"text":"8. (<i>Số nhiều</i>) <a href=\"/wiki/tr%E1%BA%ADt_t%E1%BB%B1\" title=\"trật tự\">Trật tự</a> <a href=\"/wiki/rung\" title=\"rung\">rung</a> <a href=\"/wiki/chu%C3%B4ng\" title=\"chuông\">chuông</a>.","level":1},{"text":"Ngoại động từ","level":0},{"text":"1. Đổi, <a href=\"/wiki/thay\" title=\"thay\">thay</a>, <a href=\"/wiki/thay_%C4%91%E1%BB%95i\" title=\"thay đổi\">thay đổi</a>.","level":1},{"text":"<i>to <b>change</b> one's coat</i> — thay áo","level":2},{"text":"2. Đổi, đổi <a href=\"/wiki/ch%C3%A1c\" title=\"chác\">chác</a>.","level":1},{"text":"<i>to <b>change</b> something for something</i> — đổi lấy cái gì","level":2},{"text":"<i>to <b>change</b> places with somebody</i> — đổi chỗ cho ai","level":2},{"text":"<i>thing changes hands</i> — vật thay tay đổi chủ","level":2},{"text":"3. (<i>+ to, into, from</i>) <a href=\"/wiki/bi%E1%BA%BFn\" title=\"biến\">Biến</a> đổi, đổi thành.","level":1},{"text":"4. Đổi <a href=\"/wiki/ra\" title=\"ra\">ra</a> <a href=\"/wiki/ti%E1%BB%81n_l%E1%BA%BB\" title=\"tiền lẻ\">tiền lẻ</a>.","level":1},{"text":"<i>to <b>change</b> a bank-note</i> — đổi tờ giấy bạc ra tiền lẻ","level":2},{"text":"Nội động từ","level":0},{"text":"1. <a href=\"/wiki/thay_%C4%91%E1%BB%95i\" title=\"thay đổi\">Thay đổi</a>, <a href=\"/wiki/bi%E1%BA%BFn\" title=\"biến\">biến</a> đổi.","level":1},{"text":"<i>all things <b>change</b></i> — mọi vật đều thay đổi","level":2},{"text":"2. <a href=\"/wiki/sang\" title=\"sang\">Sang</a> <a href=\"/wiki/tu%E1%BA%A7n\" title=\"tuần\">tuần</a> <a href=\"/wiki/tr%C4%83ng\" title=\"trăng\">trăng</a> <a href=\"/wiki/m%E1%BB%9Bi\" title=\"mới\">mới</a>, <a href=\"/wiki/sang\" title=\"sang\">sang</a> <a href=\"/wiki/tu%E1%BA%A7n\" title=\"tuần\">tuần</a> <a href=\"/wiki/tr%C4%83ng_non\" title=\"trăng non\">trăng non</a> (trăng).","level":1},{"text":"<i>when does the moon <b>change</b>?</i> — khi nào sang tuần trăng mới, khi nào có trăng non?","level":2},{"text":"3. <a href=\"/wiki/thay\" title=\"thay\">Thay</a> <a href=\"/wiki/qu%E1%BA%A7n_%C3%A1o\" title=\"quần áo\">quần áo</a>.","level":1},{"text":"<i>I'll <b>change</b> and come down at once</i> — tôi sẽ thay quần áo và xuống ngay","level":2},{"text":"4. Đổi <a href=\"/wiki/t%C3%A0u\" title=\"tàu\">tàu</a> <a href=\"/wiki/xe\" title=\"xe\">xe</a>.","level":1},{"text":"<i>we must <b>change</b> at the next station</i> — đến ga sau chúng ta sẽ phải đổi tàu","level":2},{"text":"Danh từ","level":0},{"text":"1. <a href=\"/wiki/s%E1%BB%B1\" title=\"sự\">Sự</a> <a href=\"/wiki/%C4%91%E1%BB%95i\" title=\"đổi\">đổi</a>, <a href=\"/wiki/s%E1%BB%B1\" title=\"sự\">sự</a> <a href=\"/wiki/%C4%91%E1%BB%95i_ch%C3%A1c\" title=\"đổi chác\">đổi chác</a>.","level":1},{"text":"2. <a href=\"/wiki/s%E1%BB%B1\" title=\"sự\">Sự</a> <a href=\"/wiki/h%E1%BB%91i_%C4%91o%C3%A1i\" title=\"hối đoái\">hối đoái</a>, <a href=\"/wiki/s%E1%BB%B1\" title=\"sự\">sự</a> <a href=\"/wiki/%C4%91%E1%BB%95i_ti%E1%BB%81n\" title=\"đổi tiền\">đổi tiền</a>.","level":1},{"text":"3. <a href=\"/wiki/gi%C3%A1\" title=\"giá\">Giá</a> <a href=\"/wiki/h%E1%BB%91i_%C4%91o%C3%A1i\" title=\"hối đoái\">hối đoái</a>.","level":1},{"text":"<i>agent de <b>change</b></i> — (kinh tế) tài chính người môi giới chứng khoán","level":2},{"text":"<i>donner le <b>change</b></i> — lừa gạt","level":2},{"text":"<i>lettre de <b>change</b></i> — hối phiếu","level":2},{"text":"<i>prendre le <b>change</b></i> — bị lừa gạt","level":2},{"text":"<i>rendre le <b>change</b> à quelqu'un</i> — hành động đáp lại ai","level":2}]