[{"text":"Danh từ","level":0},{"text":"1. Sự <a href=\"/wiki/s%E1%BB%9D_m%C3%B3\" title=\"sờ mó\">sờ mó</a>, sự <a href=\"/w/index.php?title=b%E1%BA%AFt_m%E1%BA%A1ch&amp;action=edit&amp;redlink=1\" class=\"new\" title=\"bắt mạch (trang không tồn tại)\">bắt mạch</a>.","level":1},{"text":"2. Sự <a href=\"/wiki/c%E1%BA%A3m_th%E1%BA%A5y\" title=\"cảm thấy\">cảm thấy</a>; <a href=\"/wiki/c%E1%BA%A3m_gi%C3%A1c\" title=\"cảm giác\">cảm giác</a>, <a href=\"/wiki/c%E1%BA%A3m_t%C6%B0%E1%BB%9Fng\" title=\"cảm tưởng\">cảm tưởng</a>.","level":1},{"text":"<i>a <b>feeling</b> of pain</i> — cảm giác đau đớn","level":2},{"text":"<i>to have a <b>feeling</b> of safety</i> — có cảm tưởng an toàn","level":2},{"text":"3. Sự <a href=\"/wiki/c%E1%BA%A3m_%C4%91%E1%BB%99ng\" title=\"cảm động\">cảm động</a>, sự <a href=\"/wiki/x%C3%BAc_%C4%91%E1%BB%99ng\" title=\"xúc động\">xúc động</a>.","level":1},{"text":"<i>it would be difficult for me to put into words the feelings I experienced</i> — thật mà khó viết thành lời những sự xúc động mà tôi đã trải qua","level":2},{"text":"4. Sự <a href=\"/wiki/th%C3%B4ng_c%E1%BA%A3m\" title=\"thông cảm\">thông cảm</a>.","level":1},{"text":"5. (<i>Triết học</i>) <a href=\"/wiki/c%E1%BA%A3m_t%C3%ACnh\" title=\"cảm tình\">Cảm tình</a>.","level":1},{"text":"6. <a href=\"/wiki/c%E1%BA%A3m_ngh%C4%A9\" title=\"cảm nghĩ\">Cảm nghĩ</a>, <a href=\"/wiki/%C3%BD_ki%E1%BA%BFn\" title=\"ý kiến\">ý kiến</a>.","level":1},{"text":"<i>the general <b>feeling</b> is against it</i> — ý kiến chung là không đồng ý với vấn đề ấy","level":2},{"text":"7. (<i>Nghệ thuật</i>) <a href=\"/wiki/c%E1%BA%A3m_x%C3%BAc\" title=\"cảm xúc\">Cảm xúc</a>; <a href=\"/wiki/s%E1%BB%A9c\" title=\"sức\">sức</a> <a href=\"/wiki/truy%E1%BB%81n_c%E1%BA%A3m\" title=\"truyền cảm\">truyền cảm</a>.","level":1},{"text":"8. Sự <a href=\"/wiki/nh%E1%BA%A1y_c%E1%BA%A3m\" title=\"nhạy cảm\">nhạy cảm</a>.","level":1},{"text":"<i>to have a <b>feeling</b> for music</i> — nhạy cảm về âm nhạc","level":2},{"text":"9. (<i>Số nhiều</i>) <a href=\"/wiki/l%C3%B2ng\" title=\"lòng\">Lòng</a> <a href=\"/wiki/t%E1%BB%B1_%C3%A1i\" title=\"tự ái\">tự ái</a>.","level":1},{"text":"<i>to hurt someone's feelings</i> — chạm lòng tự ái của ai","level":2},{"text":"Tính từ","level":0},{"text":"1. Có <a href=\"/wiki/c%E1%BA%A3m_gi%C3%A1c\" title=\"cảm giác\">cảm giác</a>.","level":1},{"text":"2. Có tình cảm.","level":1},{"text":"3. <a href=\"/wiki/x%C3%BAc_c%E1%BA%A3m\" title=\"xúc cảm\">Xúc cảm</a>, <a href=\"/wiki/c%E1%BA%A3m_%C4%91%E1%BB%99ng\" title=\"cảm động\">cảm động</a>.","level":1},{"text":"4. <a href=\"/wiki/nh%E1%BA%A1y_c%E1%BA%A3m\" title=\"nhạy cảm\">Nhạy cảm</a>.","level":1},{"text":"5. <a href=\"/w/index.php?title=th%E1%BA%ADt_t%C3%ACnh&amp;action=edit&amp;redlink=1\" class=\"new\" title=\"thật tình (trang không tồn tại)\">Thật tình</a>, <a href=\"/wiki/ch%C3%A2n_th%E1%BA%ADt\" title=\"chân thật\">chân thật</a>; <a href=\"/wiki/s%C3%A2u_s%E1%BA%AFc\" title=\"sâu sắc\">sâu sắc</a>.","level":1},{"text":"<i>a <b>feeling</b> pleasure</i> — niềm vui thích chân thật","level":2}]