[{"text":"Nội động từ","level":0},{"text":"1. <a href=\"/wiki/%C4%91i\" title=\"đi\">Đi</a>, đi đến, đi <a href=\"/wiki/t%E1%BB%9Bi\" title=\"tới\">tới</a>.","level":1},{"text":"<i>to <b>go</b> to Saigon</i> — đi Sài Gòn","level":2},{"text":"<i>to <b>go</b> on a journey</i> — đi du lịch","level":2},{"text":"<i>to <b>go</b> bathing</i> — đi tắm","level":2},{"text":"<i>to <b>go</b> shopping</i> — đi mua hàng","level":2},{"text":"2. <a href=\"/wiki/th%C3%A0nh\" title=\"thành\">Thành</a>, <a href=\"/w/index.php?title=th%C3%A0nh_ra&amp;action=edit&amp;redlink=1\" class=\"new\" title=\"thành ra (trang không tồn tại)\">thành ra</a>, <a href=\"/wiki/ho%C3%A1\" title=\"hoá\">hoá</a> thành.","level":1},{"text":"<i>to <b>go</b> to sea</i> — trở thành thuỷ thủ","level":2},{"text":"<i>to <b>go</b> on the stage</i> — trở thành diễn viên","level":2},{"text":"<i>to <b>go</b> on the streets</i> — làm đĩ","level":2},{"text":"<i>to <b>go</b> to the bar</i> — trở thành luật sư","level":2},{"text":"3. <a href=\"/w/index.php?title=tr%C3%B4i_qua&amp;action=edit&amp;redlink=1\" class=\"new\" title=\"trôi qua (trang không tồn tại)\">Trôi qua</a>, <a href=\"/wiki/tr%C3%B4i\" title=\"trôi\">trôi</a> đi (<a href=\"/wiki/th%E1%BB%9Di_gian\" title=\"thời gian\">thời gian</a>).","level":1},{"text":"<i>how quickly time goes!</i> — sao mà thời gian trôi nhanh thế!","level":2},{"text":"4. <a href=\"/wiki/ch%E1%BA%BFt\" title=\"chết\">Chết</a>, <a href=\"/wiki/ti%C3%AAu_tan\" title=\"tiêu tan\">tiêu tan</a>, <a href=\"/wiki/ch%E1%BA%A5m_d%E1%BB%A9t\" title=\"chấm dứt\">chấm dứt</a>, <a href=\"/wiki/m%E1%BA%A5t\" title=\"mất\">mất</a> <a href=\"/wiki/h%E1%BA%BFt\" title=\"hết\">hết</a>, <a href=\"/wiki/y%E1%BA%BFu\" title=\"yếu\">yếu</a> đi.","level":1},{"text":"<i>all hope is gone</i> — mọi hy vọng đều tiêu tan","level":2},{"text":"<i>my sight is going</i> — mắt tôi yếu đi","level":2},{"text":"5. <a href=\"/wiki/b%E1%BA%AFt_%C4%91%E1%BA%A7u\" title=\"bắt đầu\">Bắt đầu</a> (làm gì...).","level":1},{"text":"<i>one, two, three, <b>go</b>!</i> — một, hai, ba, bắt đầu!; một, hai, ba, chạy! (chạy thi)","level":2},{"text":"<i>here goes!</i> — nào bắt đầu nhé!","level":2},{"text":"6. <a href=\"/wiki/ch%E1%BA%A1y\" title=\"chạy\">Chạy</a> (<a href=\"/wiki/m%C3%A1y_m%C3%B3c\" title=\"máy móc\">máy móc</a>).","level":1},{"text":"<i>does your watch <b>go</b> well?</i> — đồng hồ của anh chạy có tốt không?","level":2},{"text":"<i>the machine goes by electricity</i> — máy chạy bằng điện","level":2},{"text":"<i>to set an engine going</i> — cho máy chạy","level":2},{"text":"7. <a href=\"/wiki/%C4%91i%E1%BB%83m\" title=\"điểm\">Điểm</a> <a href=\"/wiki/%C4%91%C3%A1nh\" title=\"đánh\">đánh</a> (<a href=\"/wiki/%C4%91%E1%BB%93ng_h%E1%BB%93\" title=\"đồng hồ\">đồng hồ</a>, <a href=\"/wiki/chu%C3%B4ng\" title=\"chuông\">chuông</a>, <a href=\"/wiki/k%E1%BA%BBng\" title=\"kẻng\">kẻng</a>); <a href=\"/wiki/n%E1%BB%95\" title=\"nổ\">nổ</a> (<a href=\"/wiki/s%C3%BAng\" title=\"súng\">súng</a>, <a href=\"/wiki/ph%C3%A1o\" title=\"pháo\">pháo</a>...).","level":1},{"text":"<i>the clock has just gone three</i> — đồng hồ vừa điểm ba giờ","level":2},{"text":"8. <a href=\"/wiki/%E1%BB%9F\" title=\"ở\">Ở</a> vào <a href=\"/wiki/t%C3%ACnh_tr%E1%BA%A1ng\" title=\"tình trạng\">tình trạng</a>, <a href=\"/wiki/s%E1%BB%91ng\" title=\"sống\">sống</a> trong <a href=\"/wiki/t%C3%ACnh_tr%E1%BA%A1ng\" title=\"tình trạng\">tình trạng</a>.","level":1},{"text":"<i>to <b>go</b> hungry</i> — sống đói khổ","level":2},{"text":"<i>to <b>go</b> with young</i> — có chửa (súc vật)","level":2},{"text":"<i>to be going with child</i> — mang thai (người)","level":2},{"text":"<i>to be six month gone with child</i> — đã mang thai sáu tháng","level":2},{"text":"9. <a href=\"/wiki/l%C3%A0m_theo\" title=\"làm theo\">Làm theo</a>, <a href=\"/wiki/h%C3%A0nh_%C4%91%E1%BB%99ng\" title=\"hành động\">hành động</a> theo; <a href=\"/wiki/h%C3%A0nh_%C4%91%E1%BB%99ng\" title=\"hành động\">hành động</a> <a href=\"/wiki/ph%C3%B9_h%E1%BB%A3p\" title=\"phù hợp\">phù hợp</a> với; <a href=\"/wiki/x%C3%A9t\" title=\"xét\">xét</a> theo.","level":1},{"text":"<i>to <b>go</b> on appearances</i> — xét bề ngoài, xét hình thức","level":2},{"text":"<i>to <b>go</b> by certain principles</i> — hành động theo một số nguyên tắc nhất định","level":2},{"text":"<i>to <b>go</b> with the tide (tomes)</i> — làm như mọi người, theo thời","level":2},{"text":"10. <a href=\"/wiki/%C4%91%E1%BB%95\" title=\"đổ\">Đổ</a>, <a href=\"/wiki/s%E1%BB%A5p\" title=\"sụp\">sụp</a>; <a href=\"/wiki/g%C3%A3y\" title=\"gãy\">gãy</a>; <a href=\"/wiki/v%E1%BB%A1_n%E1%BB%A3\" title=\"vỡ nợ\">vỡ nợ</a>, <a href=\"/wiki/ph%C3%A1_s%E1%BA%A3n\" title=\"phá sản\">phá sản</a>.","level":1},{"text":"<i>the bridge might <b>go</b> under such a weight</i> — nặng thế cầu có thể gãy","level":2},{"text":"<i>bank goes</i> — ngân hàng vỡ nợ","level":2},{"text":"11. <a href=\"/wiki/di%E1%BB%85n\" title=\"diễn\">Diễn</a> ra, <a href=\"/wiki/x%E1%BA%A3y_ra\" title=\"xảy ra\">xảy ra</a>, <a href=\"/wiki/ti%E1%BA%BFp_di%E1%BB%85n\" title=\"tiếp diễn\">tiếp diễn</a>, <a href=\"/wiki/ti%E1%BA%BFn_h%C3%A0nh\" title=\"tiến hành\">tiến hành</a>, <a href=\"/wiki/di%E1%BB%85n_bi%E1%BA%BFn\" title=\"diễn biến\">diễn biến</a>; <a href=\"/wiki/k%E1%BA%BFt_qu%E1%BA%A3\" title=\"kết quả\">kết quả</a>.","level":1},{"text":"<i>how does the affair <b>go</b>?</i> — công việc tiến hành ra sao?","level":2},{"text":"<i>the play went well</i> — vở kịch thành công tốt đẹp","level":2},{"text":"12. Đang <a href=\"/wiki/l%C6%B0u_h%C3%A0nh\" title=\"lưu hành\">lưu hành</a> (<a href=\"/wiki/ti%E1%BB%81n_b%E1%BA%A1c\" title=\"tiền bạc\">tiền bạc</a>).","level":1},{"text":"13. <a href=\"/w/index.php?title=%C4%91%E1%BA%B7t_%C4%91%E1%BB%83&amp;action=edit&amp;redlink=1\" class=\"new\" title=\"đặt để (trang không tồn tại)\">Đặt để</a>, <a href=\"/wiki/k%C3%AA\" title=\"kê\">kê</a>; để <a href=\"/wiki/v%E1%BB%ABa\" title=\"vừa\">vừa</a> vào, <a href=\"/wiki/v%E1%BB%ABa\" title=\"vừa\">vừa</a> với, có <a href=\"/wiki/ch%E1%BB%97\" title=\"chỗ\">chỗ</a>, đủ <a href=\"/wiki/ch%E1%BB%97\" title=\"chỗ\">chỗ</a>.","level":1},{"text":"<i>where is this table to <b>go</b>?</i> — kê cả cái bàn này vào đâu?","level":2},{"text":"<i>your clothes can't <b>go</b> into this small suitcase</i> — áo quần của anh không để vừa vào chiếc va li nhỏ này đâu","level":2},{"text":"<i>six goes into twelve twice</i> — mười hai chia cho sáu vừa đúng được hai","level":2},{"text":"14. <a href=\"/wiki/h%E1%BB%A3p\" title=\"hợp\">Hợp</a> với, <a href=\"/wiki/x%E1%BB%A9ng\" title=\"xứng\">xứng</a> với, <a href=\"/wiki/th%C3%ADch_h%E1%BB%A3p\" title=\"thích hợp\">thích hợp</a> với.","level":1},{"text":"<i>red goes well with brown</i> — màu đỏ rất hợp với màu nâu","level":2},{"text":"15. <a href=\"/wiki/n%C3%B3i_n%C4%83ng\" title=\"nói năng\">Nói năng</a>, <a href=\"/wiki/c%C6%B0_x%E1%BB%AD\" title=\"cư xử\">cư xử</a>; làm đến <a href=\"/wiki/m%E1%BB%A9c\" title=\"mức\">mức</a> là (...).","level":1},{"text":"<i>to have gone too for</i> — đã đi quá xa rồi, đã nói quá rồi","level":2},{"text":"<i>to <b>go</b> so far so to say...</i> — nói đến mức là...","level":2},{"text":"<i>what he say true as for as it goes</i> — trong chừng mức nào đó thì điều anh nói là đúng","level":2},{"text":"16. (<i>Thông tục</i>) Đi <a href=\"/wiki/v%E1%BB%87_sinh\" title=\"vệ sinh\">vệ sinh</a>, đi <a href=\"/wiki/c%E1%BA%A7u_ti%C3%AAu\" title=\"cầu tiêu\">cầu tiêu</a>, đi <a href=\"/wiki/%E1%BB%89a\" title=\"ỉa\">ỉa</a>, đi <a href=\"/wiki/%C4%91%C3%A1i\" title=\"đái\">đái</a>.","level":1},{"text":"<i>I really need to <b>go</b></i> — tôi cần đi cầu tiêu ngay","level":2},{"text":"17. <a href=\"/wiki/tr%E1%BA%A3\" title=\"trả\">Trả</a> (<a href=\"/wiki/gi%C3%A1\" title=\"giá\">giá</a>...); <a href=\"/wiki/ti%C3%AAu\" title=\"tiêu\">tiêu</a> vào (<a href=\"/wiki/ti%E1%BB%81n\" title=\"tiền\">tiền</a>...); <a href=\"/wiki/b%C3%A1n\" title=\"bán\">bán</a>.","level":1},{"text":"<i>to <b>go</b> as for as 100₫</i> — đã trả tới 100 đồng","level":2},{"text":"<i>all her pocket-money goes in books</i> — có bao nhiêu tiền tiêu vặt là cô ta mua sách hết","level":2},{"text":"<i>to <b>go</b> cheap</i> — bán rẻ","level":2},{"text":"<i>this goes for one shilling</i> — cái này giá một si-linh","level":2},{"text":"18. <a href=\"/wiki/thu%E1%BB%99c\" title=\"thuộc\">Thuộc</a> về.","level":1},{"text":"<i>the house went to the elder son</i> — cái nhà thuộc về người con lớn","level":2},{"text":"<i>the price went to the winner</i> — giải thưởng thuộc về phần người thắng","level":2},{"text":"19. Được <a href=\"/wiki/bi%E1%BA%BFt\" title=\"biết\">biết</a>, được <a href=\"/wiki/th%E1%BB%ABa_nh%E1%BA%ADn\" title=\"thừa nhận\">thừa nhận</a>; <a href=\"/wiki/truy%E1%BB%81n\" title=\"truyền\">truyền</a> đi, <a href=\"/wiki/n%C3%B3i\" title=\"nói\">nói</a>, <a href=\"/wiki/truy%E1%BB%81n_mi%E1%BB%87ng\" title=\"truyền miệng\">truyền miệng</a>.","level":1},{"text":"<i>as the story goes</i> — như người ta nói, có chuyện rằng","level":2},{"text":"<i>it goes without saying</i> — khỏi phải nói, tất nhiên là có, cố nhiên là","level":2},{"text":"20. <a href=\"/wiki/h%E1%BB%A3p\" title=\"hợp\">Hợp</a> <a href=\"/wiki/nh%E1%BB%8Bp_%C4%91i%E1%BB%87u\" title=\"nhịp điệu\">nhịp điệu</a>; <a href=\"/wiki/ph%E1%BB%95\" title=\"phổ\">phổ</a> theo (<a href=\"/wiki/th%C6%A1\" title=\"thơ\">thơ</a>, <a href=\"/wiki/nh%E1%BA%A1c\" title=\"nhạc\">nhạc</a>...).","level":1},{"text":"<i>to <b>go</b> to the tune of...</i> — phổ theo điệu...","level":2},{"text":"21. <a href=\"/wiki/c%C6%B0%E1%BB%9Di\" title=\"cười\">Cười</a> <a href=\"/wiki/ph%C3%A1\" title=\"phá\">phá</a> lên, cười <a href=\"/wiki/%E1%BA%A7m\" title=\"ầm\">ầm</a> lên.","level":1},{"text":"22. <a href=\"/wiki/ch%C6%A1i\" title=\"chơi\">Chơi</a> <a href=\"/wiki/l%C6%B0%E1%BB%A3t\" title=\"lượt\">lượt</a> của mình.","level":1},{"text":"<i>it's your turn to <b>go</b></i> — đến lượt anh","level":2},{"text":"23. (<i>Thông tục</i>) (+ <i><a href=\"/wiki/out\" title=\"out\">out</a></i>) <a href=\"/wiki/h%E1%BA%B9n_h%C3%B2\" title=\"hẹn hò\">Hẹn hò</a> với <a href=\"/wiki/b%E1%BA%A1n\" title=\"bạn\">bạn</a> (bạn <a href=\"/wiki/trai\" title=\"trai\">trai</a>, bạn <a href=\"/wiki/g%C3%A1i\" title=\"gái\">gái</a>).","level":1},{"text":"Ngoại động từ","level":0},{"text":"1. <a href=\"/wiki/th%C3%A0nh\" title=\"thành\">Thành</a>, <a href=\"/w/index.php?title=th%C3%A0nh_ra&amp;action=edit&amp;redlink=1\" class=\"new\" title=\"thành ra (trang không tồn tại)\">thành ra</a>, <a href=\"/wiki/ho%C3%A1\" title=\"hoá\">hoá</a> thành.","level":1},{"text":"<i>to <b>go</b> mad</i> — phát điên, hoá điên","level":2},{"text":"<i>to <b>go</b> native</i> — trở thành như người địa phương","level":2},{"text":"2. (<i>Từ lóng</i>) <a href=\"/wiki/n%C3%B3i\" title=\"nói\">Nói</a> (rằng).","level":1},{"text":"<i>I <b>go</b>, \"As if!\" And she was all like, \"Whatever!\"</i>","level":2},{"text":"3. (<i>Đánh bài</i>) <a href=\"/wiki/%C4%91i\" title=\"đi\">Đi</a>, <a href=\"/wiki/%C4%91%C3%A1nh\" title=\"đánh\">đánh</a>, <a href=\"/wiki/ra\" title=\"ra\">ra</a> (<a href=\"/wiki/qu%C3%A2n_b%C3%A0i\" title=\"quân bài\">quân bài</a>); <a href=\"/wiki/%C4%91%E1%BA%B7t\" title=\"đặt\">đặt</a> (<a href=\"/wiki/ti%E1%BB%81n\" title=\"tiền\">tiền</a>).","level":1},{"text":"<i>to <b>go</b> \"two spades\"</i> — đánh quân bài \"hai bích\"","level":2},{"text":"Danh từ","level":0},{"text":"1. Sự <a href=\"/wiki/%C4%91i\" title=\"đi\">đi</a>.","level":1},{"text":"2. <a href=\"/wiki/s%E1%BB%A9c_s%E1%BB%91ng\" title=\"sức sống\">Sức sống</a>; <a href=\"/wiki/nhi%E1%BB%87t_t%C3%ACnh\" title=\"nhiệt tình\">nhiệt tình</a>, sự <a href=\"/wiki/h%C4%83ng_h%C3%A1i\" title=\"hăng hái\">hăng hái</a>.","level":1},{"text":"<i>full of <b>go</b></i> — đầy sức sống; đầy nhiệt tình","level":2},{"text":"3. Sự <a href=\"/wiki/th%E1%BB%AD\" title=\"thử\">thử</a> (làm gì).","level":1},{"text":"<i>to have a <b>go</b> at something</i> — thử cố gắng làm việc gì","level":2},{"text":"4. <a href=\"/wiki/l%E1%BA%A7n\" title=\"lần\">Lần</a>, <a href=\"/wiki/h%C6%A1i\" title=\"hơi\">hơi</a>, <a href=\"/wiki/c%C3%BA\" title=\"cú\">cú</a>.","level":1},{"text":"<i>at one <b>go</b></i> — một lần, một hơi, một cú","level":2},{"text":"<i>to succeed at the first <b>go</b></i> — làm lần đầu đã thành công ngay","level":2},{"text":"<i>to blow out all the candles at one <b>go</b></i> — thổi một cái tắt hết các cây nến","level":2},{"text":"5. <a href=\"/wiki/l%E1%BA%A7n\" title=\"lần\">Lần</a>, <a href=\"/wiki/l%C6%B0%E1%BB%A3t\" title=\"lượt\">lượt</a>, <a href=\"/wiki/phi%C3%AAn\" title=\"phiên\">phiên</a>.","level":1},{"text":"6. <a href=\"/wiki/kh%E1%BA%A9u_ph%E1%BA%A7n\" title=\"khẩu phần\">Khẩu phần</a>, <a href=\"/wiki/su%E1%BA%A5t\" title=\"suất\">suất</a> (<a href=\"/wiki/%C4%91%E1%BB%93_%C4%83n\" title=\"đồ ăn\">đồ ăn</a>); <a href=\"/wiki/c%E1%BB%91c\" title=\"cốc\">cốc</a>, <a href=\"/wiki/ch%C3%A9n\" title=\"chén\">chén</a>, <a href=\"/wiki/h%E1%BB%9Bp\" title=\"hớp\">hớp</a> (<a href=\"/wiki/r%C6%B0%E1%BB%A3u\" title=\"rượu\">rượu</a>).","level":1},{"text":"<i>to have another <b>go</b></i> — lấy thêm một suất ăn nữa, uống thêm một chén rượu nữa","level":2},{"text":"7. (<i>Thông tục</i>) <a href=\"/wiki/vi%E1%BB%87c\" title=\"việc\">Việc</a> <a href=\"/wiki/kh%C3%B3_x%E1%BB%AD\" title=\"khó xử\">khó xử</a>, <a href=\"/wiki/vi%E1%BB%87c\" title=\"việc\">việc</a> <a href=\"/wiki/r%E1%BA%AFc_r%E1%BB%91i\" title=\"rắc rối\">rắc rối</a>.","level":1},{"text":"<i>what a <b>go</b>!</i> — sao mà rắc rối thế!","level":2},{"text":"8. (<i>Thông tục</i>) Sự <a href=\"/wiki/th%C3%A0nh_c%C3%B4ng\" title=\"thành công\">thành công</a>, sự <a href=\"/wiki/th%E1%BA%AFng_l%E1%BB%A3i\" title=\"thắng lợi\">thắng lợi</a>.","level":1},{"text":"<i>to make a <b>go</b> of it</i> — thành công (trong công việc gì...)","level":2},{"text":"9. (<i>Thông tục</i>) Sự <a href=\"/wiki/b%E1%BA%ADn_r%E1%BB%99n\" title=\"bận rộn\">bận rộn</a>, sự <a href=\"/wiki/ho%E1%BA%A1t_%C4%91%E1%BB%99ng\" title=\"hoạt động\">hoạt động</a>, sự <a href=\"/wiki/t%C3%ADch_c%E1%BB%B1c\" title=\"tích cực\">tích cực</a>.","level":1},{"text":"10. (<i>Thông tục</i>) Sự <a href=\"/wiki/cho_ph%C3%A9p\" title=\"cho phép\">cho phép</a> (<a href=\"/w/index.php?title=%C4%91i_qua&amp;action=edit&amp;redlink=1\" class=\"new\" title=\"đi qua (trang không tồn tại)\">đi qua</a>; <a href=\"/wiki/l%C3%A0m_vi%E1%BB%87c\" title=\"làm việc\">làm việc</a> gì).","level":1},{"text":"<i>we will begin as soon as the boss says it's a <b>go</b></i> — chúng ta sẽ bắt đầu lúc mà ông chủ cho phép","level":2},{"text":"Liên từ","level":0},{"text":"1. <a href=\"/wiki/r%E1%BA%B1ng\" title=\"rằng\">Rằng</a>, <a href=\"/wiki/l%C3%A0\" title=\"là\">là</a>.","level":1},{"text":"<i>Deir sé <b>go</b> bhfuil deifir air.</i> — Ông nói ông đang bận rộn.","level":2},{"text":"2. Cho đến, cho đến khi.","level":1},{"text":"<i>Fan <b>go</b> dtiocfaidh sé.</i> — Hãy chờ anh đến.","level":2},{"text":"Trợ từ","level":0},{"text":"1. (<i>Dùng để biến đổi những từ thành phó từ hay tính từ vị ngữ</i>)","level":1},{"text":"<i>bheith <b>go</b> maith</i> — có khỏe","level":2},{"text":"<i>Fuair sí bás <b>go</b> hóg</i> — Chị chết khi còn trẻ.","level":2},{"text":"<i><b>go</b> feargach</i> — tức giận, giận dữ","level":2},{"text":"<i><b>go</b> mall aréir</i> — tối trễ hôm qua","level":2},{"text":"<i><b>go</b> <a href=\"/w/index.php?title=leor&amp;action=edit&amp;redlink=1\" class=\"new\" title=\"leor (trang không tồn tại)\">leor</a></i> — đủ, đủ dùng; rất nhiều, dồi dào","level":2},{"text":"2. (<i>Đứng trước một động từ lối cầu khẩn</i>)","level":1},{"text":"<i><b>Go</b> gcuidí Dia leo.</i> — (\n<i>thường chỉ trích</i>) Cầu mong Chúa giúp đỡ họ.","level":2},{"text":"<i><b>Go</b> maire tú é.</i> — Cầu mong bạn còn sống để được thích nó.","level":2},{"text":"<i><b>Go</b> raibh maith agat.</i> — Cám ơn.","level":2},{"text":"Giới từ","level":0},{"text":"1. <a href=\"/wiki/%C4%91%E1%BA%BFn\" title=\"đến\">Đến</a>, <a href=\"/wiki/t%E1%BB%9Bi\" title=\"tới\">tới</a>, <a href=\"/wiki/v%E1%BB%81\" title=\"về\">về</a>.","level":1},{"text":"<i>dul <b>go</b> Meiriceá</i> — qua nước Mỹ","level":2},{"text":"<i>Fáilte <b>go</b> hÉirinn.</i> — Hoan nghênh anh đã đến Ireland.","level":2},{"text":"2. Cho đến, cho đến khi.","level":1},{"text":"Nội động từ","level":0},{"text":"1. (<i>Thể dục, thể thao</i>) <span class=\"use-with-mention\">Xem <span class=\"mention\"><a href=\"/w/index.php?title=partez&amp;action=edit&amp;redlink=1\" class=\"new\" title=\"partez (trang không tồn tại)\">partez</a></span>.</span>","level":1},{"text":"Tính từ","level":0},{"text":"1. <a href=\"/wiki/tr%E1%BA%A7n\" title=\"trần\">Trần</a>, <a href=\"/wiki/tr%E1%BA%A7n_tru%E1%BB%93ng\" title=\"trần truồng\">trần truồng</a>, <a href=\"/wiki/kho%E1%BA%A3_th%C3%A2n\" class=\"mw-redirect\" title=\"khoả thân\">khoả thân</a>, <a href=\"/wiki/lo%C3%A3_l%E1%BB%93\" class=\"mw-redirect\" title=\"loã lồ\">loã lồ</a>.","level":1},{"text":"Tính từ","level":0},{"text":"1. (<i>Thông tục</i>) <a href=\"/wiki/t%E1%BB%91t\" title=\"tốt\">Tốt</a>, <a href=\"/wiki/hay\" title=\"hay\">hay</a>, <a href=\"/wiki/tuy%E1%BB%87t\" title=\"tuyệt\">tuyệt</a>.","level":1},{"text":"2. (<i>Từ lóng</i>) <a href=\"/wiki/ngu_xu%E1%BA%A9n\" title=\"ngu xuẩn\">Ngu xuẩn</a>, <a href=\"/wiki/ngu_ng%E1%BB%91c\" title=\"ngu ngốc\">ngu ngốc</a>, <a href=\"/wiki/ng%E1%BB%9B_ng%E1%BA%A9n\" title=\"ngớ ngẩn\">ngớ ngẩn</a>.","level":1},{"text":"<i>Men e' du <b>go</b>, eller?</i>","level":2}]