[{"text":"Tính từ","level":0},{"text":"1. <a href=\"/w/index.php?title=r%E1%BB%91i_beng&amp;action=edit&amp;redlink=1\" class=\"new\" title=\"rối beng (trang không tồn tại)\">Rối beng</a>.","level":1},{"text":"2. <a href=\"/wiki/r%E1%BA%AFc_r%E1%BB%91i\" title=\"rắc rối\">Rắc rối</a>, <a href=\"/wiki/ph%E1%BB%A9c_t%E1%BA%A1p\" title=\"phức tạp\">phức tạp</a>, <a href=\"/wiki/kh%C3%B3_hi%E1%BB%83u\" title=\"khó hiểu\">khó hiểu</a>.","level":1},{"text":"<i>an <b>intricate</b> machine</i> — một cái máy phức tạp","level":2},{"text":"3. <a href=\"/wiki/tinh_x%E1%BA%A3o\" title=\"tinh xảo\">tinh xảo</a>, <a href=\"/wiki/chi_ti%E1%BA%BFt\" title=\"chi tiết\">chi tiết</a>, <a href=\"/wiki/t%E1%BB%89_m%E1%BB%89\" title=\"tỉ mỉ\">tỉ mỉ</a>","level":1}]