[{"text":"Động từ","level":0},{"text":"1. <span class=\"use-with-mention\"><a href=\"/wiki/ph%C3%A2n_t%E1%BB%AB\" title=\"phân từ\">Phân từ</a> <a href=\"/wiki/hi%E1%BB%87n_t%E1%BA%A1i\" title=\"hiện tại\">hiện tại</a> và hiện tại <a href=\"/wiki/ti%E1%BA%BFp_di%E1%BB%85n\" title=\"tiếp diễn\">tiếp diễn</a> của <span class=\"mention\"><a href=\"/wiki/devastate\" title=\"devastate\">devastate</a></span></span>","level":1},{"text":"Tính từ","level":0},{"text":"1. <a href=\"/wiki/t%C3%A0n_ph%C3%A1\" title=\"tàn phá\">Tàn phá</a>, <a href=\"/wiki/ph%C3%A1\" title=\"phá\">phá</a> <a href=\"/wiki/hu%E1%BB%B7\" class=\"mw-redirect\" title=\"huỷ\">huỷ</a>, <a href=\"/wiki/ph%C3%A1_ph%C3%A1ch\" title=\"phá phách\">phá phách</a>.","level":1}]